venmo/__init__.py
venmo/__version__.py
venmo/auth.py
venmo/cli.py
venmo/cookies.py
venmo/payment.py
venmo/settings.py
venmo/singletons.py
venmo/types.py
venmo/user.py
venmo-0.12.0.dist-info/METADATA
venmo-0.12.0.dist-info/WHEEL
venmo-0.12.0.dist-info/entry_points.txt
venmo-0.12.0.dist-info/top_level.txt
venmo-0.12.0.dist-info/RECORD
