Metadata-Version: 2.1
Name: venmo
Version: 0.12.0
Summary: Venmo CLI
Home-page: http://github.com/zackhsi/venmo
Author: Zack Hsi
Author-email: zackhsi@gmail.com
License: MIT
Platform: UNKNOWN
Classifier: Programming Language :: Python :: 2.7
Classifier: Programming Language :: Python :: 3.6
Requires-Dist: requests (>=2.9.1)
